{
    "deliveries": [
        {
            "start": "2021-10-13T15:32:20+00:00",
            "messageId": "0bda03eb00000000000000000000001e7668",
            "fromEmail": "acehardware@email.acehardware.com",
            "fromName": "zzz Ace",
            "replyEmail": "acehardware@email.acehardware.com",
            "recipients": [
                {
                    "type": "contact",
                    "id": "8fd7fdc3-6c51-41cd-80fc-31dd1b7dcf82"
                }
            ],
            "type": "transactional",
            "messageRuleId": "0bda03f90000000000000000000000001218",
            "fields": [
                {
                    "name": "first_name",
                    "type": "html",
                    "content": "Test1"
                },
                {
                    "name": "last_name",
                    "type": "html",
                    "content": "Customer2"
                },
                {
                    "name": "mfg_catalog_name",
                    "type": "html",
                    "content": "zzz Ace"
                },
                {
                    "name": "catalog_domain",
                    "type": "html",
                    "content": "http:\/\/www.acehardware.com\/"
                },
                {
                    "name": "catalog_logo",
                    "type": "html",
                    "content": "\/media\/mfg\/16166\/catalog_image\/logo_main_16166_Test.png"
                },
                {
                    "name": "order_id",
                    "type": "html",
                    "content": "T-Live-Testing-aaa_1634036736 (180871125)"
                },
                {
                    "name": "mfg_id",
                    "type": "html",
                    "content": "16166"
                },
                {
                    "name": "catalog_id",
                    "type": "html",
                    "content": "0"
                },
                {
                    "name": "lang_id",
                    "type": "html",
                    "content": "1"
                },
                {
                    "name": "help_url",
                    "type": "html",
                    "content": "http:\/\/www.shopatron.com\/help"
                },
                {
                    "name": "order_items",
                    "type": "html",
                    "content": "Qty  Part #                   Name                               Total\n1    8255994                  Weber SPIRIT E-210 LP BLK - Test   339.15 \nColor: Red \n\nEstimated Shipping & Handling  20.00 \nEstimated Order Total          746.10 "
                },
                {
                    "name": "item_name_1",
                    "type": "html",
                    "content": "Weber SPIRIT E-210 LP BLK - Test"
                },
                {
                    "name": "item_image_1",
                    "type": "html",
                    "content": "\/media\/shopatron\/misc\/spacer_wht.gif"
                },
                {
                    "name": "item_image_url_1",
                    "type": "html",
                    "content": "\/\/cdn-sb.mozu.com\/23027-33667\/cms\/33667\/files\/24d96086-41c0-4387-814d-e7fff6cebbe2"
                },
                {
                    "name": "prod_url_1",
                    "type": "html",
                    "content": "https:\/\/shptrn.com\/link\/cc.php?m=16166&c=0&o=OrderReadyEmail&l=http%3A%2F%2Fwww.acehardware.com%2F%3Futm_source%3D16166.0%26utm_medium%3Demail%26utm_campaign%3DOrderReadyEmail"
                },
                {
                    "name": "part_number_1",
                    "type": "html",
                    "content": "Part #: 8255994"
                },
                {
                    "name": "inventory_locator_name_1",
                    "type": "html",
                    "content": "GRILL"
                },
                {
                    "name": "item_options_1",
                    "type": "html",
                    "content": "Color: Red<br \/>"
                },
                {
                    "name": "item_quantity_1",
                    "type": "html",
                    "content": "Qty: 1"
                },
                {
                    "name": "item_subtotal_1",
                    "type": "html",
                    "content": " 339.15 "
                },
                {
                    "name": "item_subtotal_wtax_1",
                    "type": "html",
                    "content": ""
                },
                {
                    "name": "item_unit_data_1",
                    "type": "html",
                    "content": ""
                },
                {
                    "name": "item_quantity_only_1",
                    "type": "html",
                    "content": "1"
                },
                {
                    "name": "item_partNum_only_1",
                    "type": "html",
                    "content": "8255994"
                },
                {
                    "name": "icd_1",
                    "type": "html",
                    "content": ""
                },
                {
                    "name": "sku_1",
                    "type": "html",
                    "content": "8255994"
                },

               
                {
                    "name": "item_name_2",
                    "type": "html",
                    "content": "item num 2"
                },
                {
                    "name": "item_image_2",
                    "type": "html",
                    "content": "\/media\/shopatron\/misc\/spacer_wht.gif"
                },
                {
                    "name": "item_image_url_2",
                    "type": "html",
                    "content": "\/\/cdn-sb.mozu.com\/23027-33667\/cms\/33667\/files\/24d96086-41c0-4387-814d-e7fff6cebbe2"
                },
                {
                    "name": "prod_url_2",
                    "type": "html",
                    "content": "https:\/\/shptrn.com\/link\/cc.php?m=16166&c=0&o=OrderReadyEmail&l=http%3A%2F%2Fwww.acehardware.com%2F%3Futm_source%3D16166.0%26utm_medium%3Demail%26utm_campaign%3DOrderReadyEmail"
                },
                {
                    "name": "part_number_2",
                    "type": "html",
                    "content": "Part #: number2pn"
                },
                {
                    "name": "inventory_locator_name_2",
                    "type": "html",
                    "content": "GRILL"
                },
                {
                    "name": "item_options_2",
                    "type": "html",
                    "content": "Color: Red<br \/>"
                },
                {
                    "name": "item_quantity_2",
                    "type": "html",
                    "content": "Qty: 1"
                },
                {
                    "name": "item_subtotal_2",
                    "type": "html",
                    "content": " 339.15 "
                },
                {
                    "name": "item_subtotal_wtax_2",
                    "type": "html",
                    "content": ""
                },
                {
                    "name": "item_unit_data_2",
                    "type": "html",
                    "content": ""
                },
                {
                    "name": "item_quantity_only_2",
                    "type": "html",
                    "content": "1"
                },
                {
                    "name": "item_partNum_only_2",
                    "type": "html",
                    "content": "8255994"
                },
                {
                    "name": "icd_2",
                    "type": "html",
                    "content": ""
                },
                {
                    "name": "sku_2",
                    "type": "html",
                    "content": "8255994"
                },




                {
                    "name": "mfg_catalog_phone",
                    "type": "html",
                    "content": "1-888-827-4223"
                },
                {
                    "name": "catalog_name",
                    "type": "html",
                    "content": "zzz Ace"
                },
                {
                    "name": "days_remaining",
                    "type": "html",
                    "content": "8 days"
                },
                {
                    "name": "fulfiller_address_html",
                    "type": "html",
                    "content": "00033-Rick's Ace Hardware<BR>221 Lamp And Lantern Vlg<BR>Chesterfield, MO 63017<BR>US<BR>Phone: (630) 990-6600"
                },
                {
                    "name": "fulfiller_address",
                    "type": "html",
                    "content": "00033-Rick's Ace Hardware\n221 Lamp And Lantern Vlg\nChesterfield, MO 63017\nUS\nPhone: (630) 990-6600"
                },
                {
                    "name": "fulfiller_google_link",
                    "type": "html",
                    "content": "http:\/\/maps.google.com\/maps?q=221+Lamp+And+Lantern+Vlg+++Chesterfield+MO+63017"
                },
                {
                    "name": "fulfiller_name",
                    "type": "html",
                    "content": "00033-Rick's Ace Hardware"
                },
                {
                    "name": "gift_information",
                    "type": "html",
                    "content": ""
                },
                {
                    "name": "local_pickup_contact",
                    "type": "html",
                    "content": ""
                },
                {
                    "name": "local_pickup_hours_html",
                    "type": "html",
                    "content": "Sunday: 9am-6pm<BR>Monday-Friday: 7:30am-9pm<BR>Saturday: 7:30am-7pm<BR>"
                },
                {
                    "name": "location_hours_html",
                    "type": "html",
                    "content": "Sunday: 9am-6pm<BR>Monday-Friday: 7:30am-8pm<BR>Saturday: 7:30am-7pm<BR>"
                },
                {
                    "name": "local_pickup_instructions",
                    "type": "html",
                    "content": ""
                },
                {
                    "name": "local_pickup_phone",
                    "type": "html",
                    "content": ""
                },
                {
                    "name": "local_pickup_shipping_html",
                    "type": "html",
                    "content": ""
                },
                {
                    "name": "optional_marketing_html",
                    "type": "html",
                    "content": ""
                },
                {
                    "name": "order_tax",
                    "type": "html",
                    "content": " 33.90 "
                },
                {
                    "name": "order_total",
                    "type": "html",
                    "content": " 373.05 "
                },
                {
                    "name": "payment_method",
                    "type": "html",
                    "content": "<div>Ace Rewards<\/div>"
                },
                {
                    "name": "pickup_name",
                    "type": "html",
                    "content": "Test1 Customer2"
                },
                {
                    "name": "recommend_buynow",
                    "type": "html",
                    "content": "Buy now"
                },
                {
                    "name": "restocking_fee_note_html",
                    "type": "html",
                    "content": ""
                },
                {
                    "name": "backup_email",
                    "type": "html",
                    "content": ""
                },
                {
                    "name": "fulfiller_email",
                    "type": "html",
                    "content": "test.ace.account@blah.aom"
                },
                {
                    "name": "fulfiller_phone",
                    "type": "html",
                    "content": "6306609900"
                },
                {
                    "name": "item_detail",
                    "type": "html",
                    "content": "Qty  Part #                   Name                               Total\n1    8255994                  Weber SPIRIT E-210 LP BLK - Test   339.15 \nColor: Red \n\nTax                            33.90 \nEstimated Shipping & Handling  20.00 \nEstimated Order Total          373.05 "
                },
                {
                    "name": "local_pickup_hours",
                    "type": "html",
                    "content": "Sunday: 9am-6pm\nMonday-Friday: 7:30am-9pm\nSaturday: 7:30am-7pm\n"
                },
                {
                    "name": "location_hours",
                    "type": "html",
                    "content": "Sunday: 9am-6pm\nMonday-Friday: 7:30am-8pm\nSaturday: 7:30am-7pm\n"
                },
                {
                    "name": "local_pickup_shipping",
                    "type": "html",
                    "content": ""
                },
                {
                    "name": "location_in_store",
                    "type": "html",
                    "content": ""
                },
                {
                    "name": "location_name",
                    "type": "html",
                    "content": "00033-Rick's Ace Hardware"
                },
                {
                    "name": "optional_marketing",
                    "type": "html",
                    "content": ""
                },
                {
                    "name": "order_detail",
                    "type": "html",
                    "content": "Qty  Part #                   Name                               Total\n1    8255994                  Weber SPIRIT E-210 LP BLK - Test   339.15 \nColor: Red \n\nTax                            33.90 \nEstimated Shipping & Handling  20.00 \nEstimated Order Total          373.05 "
                },
                {
                    "name": "restocking_fee_note",
                    "type": "html",
                    "content": ""
                },
                {
                    "name": "mfg_email",
                    "type": "html",
                    "content": "acehardware@email.acehardware.com"
                },
                {
                    "name": "mfg_phone",
                    "type": "html",
                    "content": "1-888-827-4223"
                },
                {
                    "name": "admin_email",
                    "type": "html",
                    "content": "support@shopatron.com"
                },
                {
                    "name": "tax_breakdown",
                    "type": "html",
                    "content": ""
                },
                {
                    "name": "order_date",
                    "type": "html",
                    "content": "2021-10-12"
                },
                {
                    "name": "order_subtotal",
                    "type": "html",
                    "content": " 678.30 "
                },
                {
                    "name": "order_shipping",
                    "type": "html",
                    "content": " 0.00 "
                },
                {
                    "name": "shopatron_order_id",
                    "type": "html",
                    "content": "180871125"
                }
            ]
        }
    ]
}